README.md
setup.py
tensorsets/__init__.py
tensorsets/mnist.py
tensorsets/text8.py
tensorsets.egg-info/PKG-INFO
tensorsets.egg-info/SOURCES.txt
tensorsets.egg-info/dependency_links.txt
tensorsets.egg-info/top_level.txt